
<materials>
  <cplh6_ae type="SingleCrystalModel">
    <kinematics type="StandardKinematicModel">
      <emodel type="CubicLinearElasticModel">
        <m1>250000</m1>
        <m2>151000</m2>
        <m3>123000</m3>
        <method>components</method>
      </emodel>
      <imodel type="AsaroInelasticity">
        <rule type="PowerLawSlipRule">
          <resistance type="GeneralLinearHardening">
            <M type="SquareMatrix">
              <m>12</m>
              <type>dense</type>
              <data>0.0020493 493.78 493.78 977.67 535.14 535.14 622.77 535.14 471.67 622.77 471.67 535.14 493.78 0.0020493 493.78 535.14 622.77 471.67 535.14 977.67 535.14 471.67 622.77 535.14 493.78 493.78 0.0020493 535.14 471.67 622.77 471.67 535.14 622.77 535.14 535.14 977.67 977.67 535.14 535.14 0.0020493 493.78 493.78 622.77 471.67 535.14 622.77 535.14 471.67 535.14 622.77 471.67 493.78 0.0020493 493.78 471.67 622.77 535.14 535.14 977.67 535.14 535.14 471.67 622.77 493.78 493.78 0.0020493 535.14 535.14 977.67 471.67 535.14 622.77 622.77 535.14 471.67 622.77 471.67 535.14 0.0020493 493.78 493.78 977.67 535.14 535.14 535.14 977.67 535.14 471.67 622.77 535.14 493.78 0.0020493 493.78 535.14 622.77 471.67 471.67 535.14 622.77 535.14 535.14 977.67 493.78 493.78 0.0020493 535.14 471.67 622.77 622.77 471.67 535.14 622.77 535.14 471.67 977.67 535.14 535.14 0.0020493 493.78 493.78 471.67 622.77 535.14 535.14 977.67 535.14 535.14 622.77 471.67 493.78 0.0020493 493.78 535.14 535.14 977.67 471.67 535.14 622.77 535.14 471.67 622.77 493.78 493.78 0.0020493</data>
            </M>
            <tau_0>53.371 53.371 53.371 53.371 53.371 53.371 53.371 53.371 53.371 53.371 53.371 53.371</tau_0>
            <absval>true</absval>
          </resistance>
          <gamma0>3.25e-05</gamma0>
          <n>10.583</n>
        </rule>
      </imodel>
    </kinematics>
    <lattice type="CubicLattice">
      <a>1.0</a>
      <slip_systems>1 1 0 ; 1 1 1</slip_systems>
    </lattice>
    <alpha type="ConstantInterpolate">
      <v>0</v>
    </alpha>
    <update_rotation>true</update_rotation>
    <rtol>1e-08</rtol>
    <atol>1e-06</atol>
    <miter>50</miter>
    <verbose>false</verbose>
    <linesearch>false</linesearch>
    <max_divide>4</max_divide>
    <postprocessors/>
    <elastic_predictor>false</elastic_predictor>
    <fallback_elastic_predictor>true</fallback_elastic_predictor>
    <force_divide>0</force_divide>
    <elastic_predictor_first_step>false</elastic_predictor_first_step>
  </cplh6_ae>
</materials>
