
<materials>
  <cplh6_ae type="SingleCrystalModel">
    <kinematics type="StandardKinematicModel">
      <emodel type="CubicLinearElasticModel">
        <m1>250000</m1>
        <m2>151000</m2>
        <m3>123000</m3>
        <method>components</method>
      </emodel>
      <imodel type="AsaroInelasticity">
        <rule type="PowerLawSlipRule">
          <resistance type="GeneralLinearHardening">
            <M type="SquareMatrix">
              <m>12</m>
              <type>dense</type>
              <data>578.0673533778032 3.16743920656596 3.16743920656596 508.3226913673059 54.735220532204515 54.735220532204515 790.4941719007575 54.735220532204515 194.35406458941 790.4941719007575 194.35406458941 54.735220532204515 3.16743920656596 578.0673533778032 3.16743920656596 54.735220532204515 790.4941719007575 194.35406458941 54.735220532204515 508.3226913673059 54.735220532204515 194.35406458941 790.4941719007575 54.735220532204515 3.16743920656596 3.16743920656596 578.0673533778032 54.735220532204515 194.35406458941 790.4941719007575 194.35406458941 54.735220532204515 790.4941719007575 54.735220532204515 54.735220532204515 508.3226913673059 508.3226913673059 54.735220532204515 54.735220532204515 578.0673533778032 3.16743920656596 3.16743920656596 790.4941719007575 194.35406458941 54.735220532204515 790.4941719007575 54.735220532204515 194.35406458941 54.735220532204515 790.4941719007575 194.35406458941 3.16743920656596 578.0673533778032 3.16743920656596 194.35406458941 790.4941719007575 54.735220532204515 54.735220532204515 508.3226913673059 54.735220532204515 54.735220532204515 194.35406458941 790.4941719007575 3.16743920656596 3.16743920656596 578.0673533778032 54.735220532204515 54.735220532204515 508.3226913673059 194.35406458941 54.735220532204515 790.4941719007575 790.4941719007575 54.735220532204515 194.35406458941 790.4941719007575 194.35406458941 54.735220532204515 578.0673533778032 3.16743920656596 3.16743920656596 508.3226913673059 54.735220532204515 54.735220532204515 54.735220532204515 508.3226913673059 54.735220532204515 194.35406458941 790.4941719007575 54.735220532204515 3.16743920656596 578.0673533778032 3.16743920656596 54.735220532204515 790.4941719007575 194.35406458941 194.35406458941 54.735220532204515 790.4941719007575 54.735220532204515 54.735220532204515 508.3226913673059 3.16743920656596 3.16743920656596 578.0673533778032 54.735220532204515 194.35406458941 790.4941719007575 790.4941719007575 194.35406458941 54.735220532204515 790.4941719007575 54.735220532204515 194.35406458941 508.3226913673059 54.735220532204515 54.735220532204515 578.0673533778032 3.16743920656596 3.16743920656596 194.35406458941 790.4941719007575 54.735220532204515 54.735220532204515 508.3226913673059 54.735220532204515 54.735220532204515 790.4941719007575 194.35406458941 3.16743920656596 578.0673533778032 3.16743920656596 54.735220532204515 54.735220532204515 508.3226913673059 194.35406458941 54.735220532204515 790.4941719007575 54.735220532204515 194.35406458941 790.4941719007575 3.16743920656596 3.16743920656596 578.0673533778032</data>
            </M>
            <tau_0>406.4423786532712 406.4423786532712 406.4423786532712 406.4423786532712 406.4423786532712 406.4423786532712 406.4423786532712 406.4423786532712 406.4423786532712 406.4423786532712 406.4423786532712 406.4423786532712</tau_0>
            <absval>true</absval>
          </resistance>
          <gamma0>3.25e-05</gamma0>
          <n>2.083640443969581</n>
        </rule>
      </imodel>
    </kinematics>
    <lattice type="CubicLattice">
      <a>1.0</a>
      <slip_systems>1 1 0 ; 1 1 1</slip_systems>
    </lattice>
    <alpha type="ConstantInterpolate">
      <v>0</v>
    </alpha>
    <update_rotation>true</update_rotation>
    <rtol>1e-08</rtol>
    <atol>1e-06</atol>
    <miter>50</miter>
    <verbose>false</verbose>
    <linesearch>false</linesearch>
    <max_divide>4</max_divide>
    <postprocessors/>
    <elastic_predictor>false</elastic_predictor>
    <fallback_elastic_predictor>true</fallback_elastic_predictor>
    <force_divide>0</force_divide>
    <elastic_predictor_first_step>false</elastic_predictor_first_step>
  </cplh6_ae>
</materials>
