
<materials>
  <cvp_ae_lh6_cp type="SingleCrystalModel">
    <kinematics type="StandardKinematicModel">
      <emodel type="CubicLinearElasticModel">
        <m1>250000</m1>
        <m2>151000</m2>
        <m3>123000</m3>
        <method>components</method>
      </emodel>
      <imodel type="AsaroInelasticity">
        <rule type="PowerLawSlipRule">
          <resistance type="GeneralLinearHardening">
            <M type="SquareMatrix">
              <m>12</m>
              <type>dense</type>
              <data>98.0594622438656 213.70741793437955 213.70741793437955 333.43951473076004 142.6426247713497 142.6426247713497 305.1776800981099 142.6426247713497 20.4071367760301 305.1776800981099 20.4071367760301 142.6426247713497 213.70741793437955 98.0594622438656 213.70741793437955 142.6426247713497 305.1776800981099 20.4071367760301 142.6426247713497 333.43951473076004 142.6426247713497 20.4071367760301 305.1776800981099 142.6426247713497 213.70741793437955 213.70741793437955 98.0594622438656 142.6426247713497 20.4071367760301 305.1776800981099 20.4071367760301 142.6426247713497 305.1776800981099 142.6426247713497 142.6426247713497 333.43951473076004 333.43951473076004 142.6426247713497 142.6426247713497 98.0594622438656 213.70741793437955 213.70741793437955 305.1776800981099 20.4071367760301 142.6426247713497 305.1776800981099 142.6426247713497 20.4071367760301 142.6426247713497 305.1776800981099 20.4071367760301 213.70741793437955 98.0594622438656 213.70741793437955 20.4071367760301 305.1776800981099 142.6426247713497 142.6426247713497 333.43951473076004 142.6426247713497 142.6426247713497 20.4071367760301 305.1776800981099 213.70741793437955 213.70741793437955 98.0594622438656 142.6426247713497 142.6426247713497 333.43951473076004 20.4071367760301 142.6426247713497 305.1776800981099 305.1776800981099 142.6426247713497 20.4071367760301 305.1776800981099 20.4071367760301 142.6426247713497 98.0594622438656 213.70741793437955 213.70741793437955 333.43951473076004 142.6426247713497 142.6426247713497 142.6426247713497 333.43951473076004 142.6426247713497 20.4071367760301 305.1776800981099 142.6426247713497 213.70741793437955 98.0594622438656 213.70741793437955 142.6426247713497 305.1776800981099 20.4071367760301 20.4071367760301 142.6426247713497 305.1776800981099 142.6426247713497 142.6426247713497 333.43951473076004 213.70741793437955 213.70741793437955 98.0594622438656 142.6426247713497 20.4071367760301 305.1776800981099 305.1776800981099 20.4071367760301 142.6426247713497 305.1776800981099 142.6426247713497 20.4071367760301 333.43951473076004 142.6426247713497 142.6426247713497 98.0594622438656 213.70741793437955 213.70741793437955 20.4071367760301 305.1776800981099 142.6426247713497 142.6426247713497 333.43951473076004 142.6426247713497 142.6426247713497 305.1776800981099 20.4071367760301 213.70741793437955 98.0594622438656 213.70741793437955 142.6426247713497 142.6426247713497 333.43951473076004 20.4071367760301 142.6426247713497 305.1776800981099 142.6426247713497 20.4071367760301 305.1776800981099 213.70741793437955 213.70741793437955 98.0594622438656</data>
            </M>
            <tau_0>31.635030893118177 31.635030893118177 31.635030893118177 31.635030893118177 31.635030893118177 31.635030893118177 31.635030893118177 31.635030893118177 31.635030893118177 31.635030893118177 31.635030893118177 31.635030893118177</tau_0>
            <absval>true</absval>
          </resistance>
          <gamma0>3.333e-05</gamma0>
          <n>13.781168285395166</n>
        </rule>
      </imodel>
    </kinematics>
    <lattice type="CubicLattice">
      <a>1.0</a>
      <slip_systems>1 1 0 ; 1 1 1</slip_systems>
    </lattice>
    <alpha type="ConstantInterpolate">
      <v>0</v>
    </alpha>
    <update_rotation>true</update_rotation>
    <rtol>1e-08</rtol>
    <atol>1e-06</atol>
    <miter>50</miter>
    <verbose>false</verbose>
    <linesearch>false</linesearch>
    <max_divide>4</max_divide>
    <postprocessors/>
    <elastic_predictor>false</elastic_predictor>
    <fallback_elastic_predictor>true</fallback_elastic_predictor>
    <force_divide>0</force_divide>
    <elastic_predictor_first_step>false</elastic_predictor_first_step>
  </cvp_ae_lh6_cp>
  <cvp_ae_lh6_vp type="GeneralIntegrator">
		<elastic type="IsotropicLinearElasticModel">
      <m1_type>youngs</m1_type>
      <m1>211000.0</m1>
      <m2_type>poissons</m2_type>
      <m2>0.3</m2>
		</elastic>
		<rule type="TVPFlowRule">
			<elastic type="IsotropicLinearElasticModel">
        <m1_type>youngs</m1_type>
        <m1>211000.0</m1>
        <m2_type>poissons</m2_type>
        <m2>0.3</m2>
			</elastic>
			<flow type="PerzynaFlowRule">
				<surface type="IsoJ2"/>
				<hardening type="VoceIsotropicHardeningRule">
					<s0>93.655</s0>
					<R>3957.3</R>
					<d>0.5651</d>
				</hardening>
				<g type="GPowerLaw">
					<n>7.3648</n>
					<eta>721.59</eta>
				</g>
			</flow>
		</rule>
		<alpha type="ConstantInterpolate">
			<v>0</v>
		</alpha>
		<truesdell>false</truesdell>
		<rtol>1e-08</rtol>
		<atol>1e-08</atol>
		<miter>50</miter>
		<verbose>false</verbose>
		<linesearch>false</linesearch>
		<max_divide>4</max_divide>
		<force_divide>false</force_divide>
		<skip_first_step>false</skip_first_step>
  </cvp_ae_lh6_vp>
</materials>
