
<materials>
  <cvp_ae_lh6_cp type="SingleCrystalModel">
    <kinematics type="StandardKinematicModel">
      <emodel type="CubicLinearElasticModel">
        <m1>250000</m1>
        <m2>151000</m2>
        <m3>123000</m3>
        <method>components</method>
      </emodel>
      <imodel type="AsaroInelasticity">
        <rule type="PowerLawSlipRule">
          <resistance type="GeneralLinearHardening">
            <M type="SquareMatrix">
              <m>12</m>
              <type>dense</type>
              <data>38.575521168897644 202.35365375779585 202.35365375779585 237.99294071099112 317.37851199934886 317.37851199934886 243.09142979714431 317.37851199934886 57.8727053569391 243.09142979714431 57.8727053569391 317.37851199934886 202.35365375779585 38.575521168897644 202.35365375779585 317.37851199934886 243.09142979714431 57.8727053569391 317.37851199934886 237.99294071099112 317.37851199934886 57.8727053569391 243.09142979714431 317.37851199934886 202.35365375779585 202.35365375779585 38.575521168897644 317.37851199934886 57.8727053569391 243.09142979714431 57.8727053569391 317.37851199934886 243.09142979714431 317.37851199934886 317.37851199934886 237.99294071099112 237.99294071099112 317.37851199934886 317.37851199934886 38.575521168897644 202.35365375779585 202.35365375779585 243.09142979714431 57.8727053569391 317.37851199934886 243.09142979714431 317.37851199934886 57.8727053569391 317.37851199934886 243.09142979714431 57.8727053569391 202.35365375779585 38.575521168897644 202.35365375779585 57.8727053569391 243.09142979714431 317.37851199934886 317.37851199934886 237.99294071099112 317.37851199934886 317.37851199934886 57.8727053569391 243.09142979714431 202.35365375779585 202.35365375779585 38.575521168897644 317.37851199934886 317.37851199934886 237.99294071099112 57.8727053569391 317.37851199934886 243.09142979714431 243.09142979714431 317.37851199934886 57.8727053569391 243.09142979714431 57.8727053569391 317.37851199934886 38.575521168897644 202.35365375779585 202.35365375779585 237.99294071099112 317.37851199934886 317.37851199934886 317.37851199934886 237.99294071099112 317.37851199934886 57.8727053569391 243.09142979714431 317.37851199934886 202.35365375779585 38.575521168897644 202.35365375779585 317.37851199934886 243.09142979714431 57.8727053569391 57.8727053569391 317.37851199934886 243.09142979714431 317.37851199934886 317.37851199934886 237.99294071099112 202.35365375779585 202.35365375779585 38.575521168897644 317.37851199934886 57.8727053569391 243.09142979714431 243.09142979714431 57.8727053569391 317.37851199934886 243.09142979714431 317.37851199934886 57.8727053569391 237.99294071099112 317.37851199934886 317.37851199934886 38.575521168897644 202.35365375779585 202.35365375779585 57.8727053569391 243.09142979714431 317.37851199934886 317.37851199934886 237.99294071099112 317.37851199934886 317.37851199934886 243.09142979714431 57.8727053569391 202.35365375779585 38.575521168897644 202.35365375779585 317.37851199934886 317.37851199934886 237.99294071099112 57.8727053569391 317.37851199934886 243.09142979714431 317.37851199934886 57.8727053569391 243.09142979714431 202.35365375779585 202.35365375779585 38.575521168897644</data>
            </M>
            <tau_0>115.23689770382019 115.23689770382019 115.23689770382019 115.23689770382019 115.23689770382019 115.23689770382019 115.23689770382019 115.23689770382019 115.23689770382019 115.23689770382019 115.23689770382019 115.23689770382019</tau_0>
            <absval>true</absval>
          </resistance>
          <gamma0>3.333e-05</gamma0>
          <n>13.901888784731433</n>
        </rule>
      </imodel>
    </kinematics>
    <lattice type="CubicLattice">
      <a>1.0</a>
      <slip_systems>1 1 0 ; 1 1 1</slip_systems>
    </lattice>
    <alpha type="ConstantInterpolate">
      <v>0</v>
    </alpha>
    <update_rotation>true</update_rotation>
    <rtol>1e-08</rtol>
    <atol>1e-06</atol>
    <miter>50</miter>
    <verbose>false</verbose>
    <linesearch>false</linesearch>
    <max_divide>4</max_divide>
    <postprocessors/>
    <elastic_predictor>false</elastic_predictor>
    <fallback_elastic_predictor>true</fallback_elastic_predictor>
    <force_divide>0</force_divide>
    <elastic_predictor_first_step>false</elastic_predictor_first_step>
  </cvp_ae_lh6_cp>
  <cvp_ae_lh6_vp type="GeneralIntegrator">
		<elastic type="IsotropicLinearElasticModel">
      <m1_type>youngs</m1_type>
      <m1>211000.0</m1>
      <m2_type>poissons</m2_type>
      <m2>0.3</m2>
		</elastic>
		<rule type="TVPFlowRule">
			<elastic type="IsotropicLinearElasticModel">
        <m1_type>youngs</m1_type>
        <m1>211000.0</m1>
        <m2_type>poissons</m2_type>
        <m2>0.3</m2>
			</elastic>
			<flow type="PerzynaFlowRule">
				<surface type="IsoJ2"/>
				<hardening type="VoceIsotropicHardeningRule">
					<s0>93.655</s0>
					<R>3957.3</R>
					<d>0.5651</d>
				</hardening>
				<g type="GPowerLaw">
					<n>7.3648</n>
					<eta>721.59</eta>
				</g>
			</flow>
		</rule>
		<alpha type="ConstantInterpolate">
			<v>0</v>
		</alpha>
		<truesdell>false</truesdell>
		<rtol>1e-08</rtol>
		<atol>1e-08</atol>
		<miter>50</miter>
		<verbose>false</verbose>
		<linesearch>false</linesearch>
		<max_divide>4</max_divide>
		<force_divide>false</force_divide>
		<skip_first_step>false</skip_first_step>
  </cvp_ae_lh6_vp>
</materials>
